time_economy/__init__.py
time_economy/base.py
time_economy/comparison_plotter.py
time_economy/multi_config_analysis.py
time_economy/plotter.py
time_economy/time_vector_simulation.py
time_economy/utils.py
time_economy-1.0.0.dist-info/licenses/LICENSE
time_economy-1.0.0.dist-info/METADATA
time_economy-1.0.0.dist-info/WHEEL
time_economy-1.0.0.dist-info/entry_points.txt
time_economy-1.0.0.dist-info/top_level.txt
time_economy-1.0.0.dist-info/RECORD
