Metadata-Version: 2.4
Name: time-economy
Version: 1.0.0
Summary: A comprehensive toolkit for time-based economy simulation, focusing on wealth distribution and economic modeling
Home-page: https://github.com/double-n-a/time-economy
Author: Double-N-A
Classifier: Development Status :: 3 - Alpha
Classifier: Intended Audience :: Science/Research
Classifier: License :: OSI Approved :: MIT License
Classifier: Operating System :: OS Independent
Classifier: Programming Language :: Python :: 3.12
Classifier: Programming Language :: Python :: 3.13
Classifier: Programming Language :: Python :: 3.14
Classifier: Topic :: Scientific/Engineering
Classifier: Topic :: Scientific/Engineering :: Mathematics
Classifier: Topic :: Scientific/Engineering :: Physics
Requires-Python: >=3.12
License-File: LICENSE
Requires-Dist: numpy>=1.20.0
Requires-Dist: matplotlib>=3.5.0
Requires-Dist: pandas>=1.3.0
Requires-Dist: seaborn>=0.11.0
Requires-Dist: joblib>=1.0.0
Requires-Dist: scipy>=1.7.0
Requires-Dist: IPython>=7.0.0
Provides-Extra: gpu
Requires-Dist: cupy>=10.0.0; extra == "gpu"
Provides-Extra: dev
Requires-Dist: pytest>=6.0; extra == "dev"
Requires-Dist: black; extra == "dev"
Requires-Dist: flake8; extra == "dev"
Dynamic: author
Dynamic: classifier
Dynamic: description
Dynamic: description-content-type
Dynamic: home-page
Dynamic: license-file
Dynamic: provides-extra
Dynamic: requires-dist
Dynamic: requires-python
Dynamic: summary
